wage/__init__.py
wage/formatters.py
wage/interface.py
wage/salary.py
wage-0.7.dist-info/LICENSE.md
wage-0.7.dist-info/METADATA
wage-0.7.dist-info/WHEEL
wage-0.7.dist-info/entry_points.txt
wage-0.7.dist-info/top_level.txt
wage-0.7.dist-info/RECORD
