Metadata-Version: 2.1
Name: wage
Version: 0.7
Summary: A python module for modeling and converting salary/income information
Home-page: https://github.com/miliarch/wage
Author: Marcus Bowman
Author-email: miliarch.mb@gmail.com
License: MIT
Project-URL: Source Code, https://github.com/miliarch/wage
Keywords: wage salary income convert model
Requires-Python: >=3.7
License-File: LICENSE.md
